QianduankaifaZheZhinan2017/README.md
QianduankaifaZheZhinan2017/__init__.py
QianduankaifaZheZhinan2017/__main__.py
QianduankaifaZheZhinan2017/file.epub
QianduankaifaZheZhinan2017/index.html
QianduankaifaZheZhinan2017/css/__init__.py
QianduankaifaZheZhinan2017/css/annotations.css
QianduankaifaZheZhinan2017/css/main.css
QianduankaifaZheZhinan2017/css/normalize.css
QianduankaifaZheZhinan2017/css/popup.css
QianduankaifaZheZhinan2017/font/__init__.py
QianduankaifaZheZhinan2017/font/fontello.eot
QianduankaifaZheZhinan2017/font/fontello.svg
QianduankaifaZheZhinan2017/font/fontello.ttf
QianduankaifaZheZhinan2017/font/fontello.woff
QianduankaifaZheZhinan2017/img/__init__.py
QianduankaifaZheZhinan2017/img/annotator-glyph-sprite.png
QianduankaifaZheZhinan2017/img/annotator-icon-sprite.png
QianduankaifaZheZhinan2017/img/apple-touch-icon.png
QianduankaifaZheZhinan2017/img/cancelfullscreen.png
QianduankaifaZheZhinan2017/img/close.png
QianduankaifaZheZhinan2017/img/fullscreen.png
QianduankaifaZheZhinan2017/img/loader.gif
QianduankaifaZheZhinan2017/img/menu-icon.png
QianduankaifaZheZhinan2017/img/save.png
QianduankaifaZheZhinan2017/img/saved.png
QianduankaifaZheZhinan2017/img/settings-s.png
QianduankaifaZheZhinan2017/img/settings.png
QianduankaifaZheZhinan2017/img/star.png
QianduankaifaZheZhinan2017/js/__init__.py
QianduankaifaZheZhinan2017/js/epub.js
QianduankaifaZheZhinan2017/js/epub.min.js
QianduankaifaZheZhinan2017/js/epub.min.map
QianduankaifaZheZhinan2017/js/hooks.min.js
QianduankaifaZheZhinan2017/js/hooks.min.map
QianduankaifaZheZhinan2017/js/reader.js
QianduankaifaZheZhinan2017/js/reader.js.map
QianduankaifaZheZhinan2017/js/reader.min.js
QianduankaifaZheZhinan2017/js/reader.min.map
QianduankaifaZheZhinan2017/js/hooks/__init__.py
QianduankaifaZheZhinan2017/js/hooks/extensions/__init__.py
QianduankaifaZheZhinan2017/js/hooks/extensions/highlight.js
QianduankaifaZheZhinan2017/js/libs/__init__.py
QianduankaifaZheZhinan2017/js/libs/jquery.min.js
qianduankaifa_zhe_zhinan_2017-2024.3.2.0.dist-info/METADATA
qianduankaifa_zhe_zhinan_2017-2024.3.2.0.dist-info/WHEEL
qianduankaifa_zhe_zhinan_2017-2024.3.2.0.dist-info/entry_points.txt
qianduankaifa_zhe_zhinan_2017-2024.3.2.0.dist-info/top_level.txt
qianduankaifa_zhe_zhinan_2017-2024.3.2.0.dist-info/RECORD
